{
	"pattrstorage" : 	{
		"name" : "shape",
		"slots" : 		{
			"1" : 			{
				"id" : 1,
				"data" : 				{
					"shape_basis" : [ 0 ],
					"shape_period" : [ 1 ],
					"shape_scale" : [ 1.0 ],
					"shape_shape" : [ 0 ]
				}

			}
,
			"2" : 			{
				"id" : 2,
				"data" : 				{
					"shape_basis" : [ 1 ],
					"shape_period" : [ 2 ],
					"shape_scale" : [ 2.0 ],
					"shape_shape" : [ 0 ]
				}

			}
,
			"3" : 			{
				"id" : 3,
				"data" : 				{
					"shape_basis" : [ 2 ],
					"shape_period" : [ 4 ],
					"shape_scale" : [ 4.0 ],
					"shape_shape" : [ 0 ]
				}

			}
,
			"4" : 			{
				"id" : 4,
				"data" : 				{
					"shape_basis" : [ 3 ],
					"shape_period" : [ 1 ],
					"shape_scale" : [ 2.0 ],
					"shape_shape" : [ 0 ]
				}

			}
,
			"5" : 			{
				"id" : 5,
				"data" : 				{
					"shape_basis" : [ 4 ],
					"shape_period" : [ 3 ],
					"shape_scale" : [ 1.0 ],
					"shape_shape" : [ 0 ]
				}

			}
,
			"6" : 			{
				"id" : 6,
				"data" : 				{
					"shape_basis" : [ 5 ],
					"shape_period" : [ 4 ],
					"shape_scale" : [ 4.0 ],
					"shape_shape" : [ 0 ]
				}

			}
,
			"7" : 			{
				"id" : 7,
				"data" : 				{
					"shape_basis" : [ 6 ],
					"shape_period" : [ 4 ],
					"shape_scale" : [ 1.0 ],
					"shape_shape" : [ 1 ]
				}

			}
,
			"8" : 			{
				"id" : 8,
				"data" : 				{
					"shape_basis" : [ 7 ],
					"shape_period" : [ 6 ],
					"shape_scale" : [ 1.0 ],
					"shape_shape" : [ 0 ]
				}

			}
,
			"9" : 			{
				"id" : 9,
				"data" : 				{
					"shape_basis" : [ 8 ],
					"shape_period" : [ 6 ],
					"shape_scale" : [ 1.0 ],
					"shape_shape" : [ 0 ]
				}

			}
,
			"10" : 			{
				"id" : 10,
				"data" : 				{
					"shape_basis" : [ 0 ],
					"shape_period" : [ 1 ],
					"shape_scale" : [ 1.0 ],
					"shape_shape" : [ 1 ]
				}

			}
,
			"11" : 			{
				"id" : 11,
				"data" : 				{
					"shape_basis" : [ 1 ],
					"shape_period" : [ 2 ],
					"shape_scale" : [ 2.0 ],
					"shape_shape" : [ 1 ]
				}

			}
,
			"12" : 			{
				"id" : 12,
				"data" : 				{
					"shape_basis" : [ 2 ],
					"shape_period" : [ 4 ],
					"shape_scale" : [ 4.0 ],
					"shape_shape" : [ 1 ]
				}

			}
,
			"13" : 			{
				"id" : 13,
				"data" : 				{
					"shape_basis" : [ 3 ],
					"shape_period" : [ 1 ],
					"shape_scale" : [ 2.0 ],
					"shape_shape" : [ 1 ]
				}

			}
,
			"14" : 			{
				"id" : 14,
				"data" : 				{
					"shape_basis" : [ 4 ],
					"shape_period" : [ 3 ],
					"shape_scale" : [ 1.0 ],
					"shape_shape" : [ 1 ]
				}

			}
,
			"15" : 			{
				"id" : 15,
				"data" : 				{
					"shape_basis" : [ 5 ],
					"shape_period" : [ 4 ],
					"shape_scale" : [ 4.0 ],
					"shape_shape" : [ 1 ]
				}

			}
,
			"16" : 			{
				"id" : 16,
				"data" : 				{
					"shape_basis" : [ 6 ],
					"shape_period" : [ 4 ],
					"shape_scale" : [ 1.0 ],
					"shape_shape" : [ 0 ]
				}

			}
,
			"17" : 			{
				"id" : 17,
				"data" : 				{
					"shape_basis" : [ 7 ],
					"shape_period" : [ 6 ],
					"shape_scale" : [ 1.0 ],
					"shape_shape" : [ 1 ]
				}

			}
,
			"18" : 			{
				"id" : 18,
				"data" : 				{
					"shape_basis" : [ 8 ],
					"shape_period" : [ 6 ],
					"shape_scale" : [ 1.0 ],
					"shape_shape" : [ 1 ]
				}

			}
,
			"19" : 			{
				"id" : 19,
				"data" : 				{
					"shape_basis" : [ 0 ],
					"shape_period" : [ 1 ],
					"shape_scale" : [ 1.0 ],
					"shape_shape" : [ 2 ]
				}

			}
,
			"20" : 			{
				"id" : 20,
				"data" : 				{
					"shape_basis" : [ 1 ],
					"shape_period" : [ 2 ],
					"shape_scale" : [ 2.0 ],
					"shape_shape" : [ 2 ]
				}

			}
,
			"21" : 			{
				"id" : 21,
				"data" : 				{
					"shape_basis" : [ 2 ],
					"shape_period" : [ 4 ],
					"shape_scale" : [ 4.0 ],
					"shape_shape" : [ 2 ]
				}

			}
,
			"22" : 			{
				"id" : 22,
				"data" : 				{
					"shape_basis" : [ 3 ],
					"shape_period" : [ 1 ],
					"shape_scale" : [ 2.0 ],
					"shape_shape" : [ 2 ]
				}

			}
,
			"23" : 			{
				"id" : 23,
				"data" : 				{
					"shape_basis" : [ 4 ],
					"shape_period" : [ 3 ],
					"shape_scale" : [ 1.0 ],
					"shape_shape" : [ 2 ]
				}

			}
,
			"24" : 			{
				"id" : 24,
				"data" : 				{
					"shape_basis" : [ 5 ],
					"shape_period" : [ 4 ],
					"shape_scale" : [ 4.0 ],
					"shape_shape" : [ 2 ]
				}

			}
,
			"25" : 			{
				"id" : 25,
				"data" : 				{
					"shape_basis" : [ 6 ],
					"shape_period" : [ 4 ],
					"shape_scale" : [ 1.0 ],
					"shape_shape" : [ 2 ]
				}

			}
,
			"26" : 			{
				"id" : 26,
				"data" : 				{
					"shape_basis" : [ 7 ],
					"shape_period" : [ 6 ],
					"shape_scale" : [ 1.0 ],
					"shape_shape" : [ 2 ]
				}

			}
,
			"27" : 			{
				"id" : 27,
				"data" : 				{
					"shape_basis" : [ 8 ],
					"shape_period" : [ 6 ],
					"shape_scale" : [ 1.0 ],
					"shape_shape" : [ 2 ]
				}

			}
,
			"28" : 			{
				"id" : 28,
				"data" : 				{
					"shape_basis" : [ 0 ],
					"shape_period" : [ 1 ],
					"shape_scale" : [ 1.0 ],
					"shape_shape" : [ 3 ]
				}

			}
,
			"29" : 			{
				"id" : 29,
				"data" : 				{
					"shape_basis" : [ 1 ],
					"shape_period" : [ 2 ],
					"shape_scale" : [ 2.0 ],
					"shape_shape" : [ 3 ]
				}

			}
,
			"30" : 			{
				"id" : 30,
				"data" : 				{
					"shape_basis" : [ 2 ],
					"shape_period" : [ 4 ],
					"shape_scale" : [ 4.0 ],
					"shape_shape" : [ 3 ]
				}

			}
,
			"31" : 			{
				"id" : 31,
				"data" : 				{
					"shape_basis" : [ 3 ],
					"shape_period" : [ 1 ],
					"shape_scale" : [ 2.0 ],
					"shape_shape" : [ 3 ]
				}

			}
,
			"32" : 			{
				"id" : 32,
				"data" : 				{
					"shape_basis" : [ 4 ],
					"shape_period" : [ 3 ],
					"shape_scale" : [ 1.0 ],
					"shape_shape" : [ 3 ]
				}

			}
,
			"33" : 			{
				"id" : 33,
				"data" : 				{
					"shape_basis" : [ 5 ],
					"shape_period" : [ 4 ],
					"shape_scale" : [ 4.0 ],
					"shape_shape" : [ 3 ]
				}

			}
,
			"34" : 			{
				"id" : 34,
				"data" : 				{
					"shape_basis" : [ 6 ],
					"shape_period" : [ 4 ],
					"shape_scale" : [ 1.0 ],
					"shape_shape" : [ 3 ]
				}

			}
,
			"35" : 			{
				"id" : 35,
				"data" : 				{
					"shape_basis" : [ 7 ],
					"shape_period" : [ 6 ],
					"shape_scale" : [ 1.0 ],
					"shape_shape" : [ 3 ]
				}

			}
,
			"36" : 			{
				"id" : 36,
				"data" : 				{
					"shape_basis" : [ 8 ],
					"shape_period" : [ 6 ],
					"shape_scale" : [ 1.0 ],
					"shape_shape" : [ 3 ]
				}

			}
,
			"37" : 			{
				"id" : 37,
				"data" : 				{
					"shape_basis" : [ 0 ],
					"shape_period" : [ 1 ],
					"shape_scale" : [ 1.0 ],
					"shape_shape" : [ 4 ]
				}

			}
,
			"38" : 			{
				"id" : 38,
				"data" : 				{
					"shape_basis" : [ 1 ],
					"shape_period" : [ 2 ],
					"shape_scale" : [ 2.0 ],
					"shape_shape" : [ 4 ]
				}

			}
,
			"39" : 			{
				"id" : 39,
				"data" : 				{
					"shape_basis" : [ 2 ],
					"shape_period" : [ 4 ],
					"shape_scale" : [ 4.0 ],
					"shape_shape" : [ 4 ]
				}

			}
,
			"40" : 			{
				"id" : 40,
				"data" : 				{
					"shape_basis" : [ 3 ],
					"shape_period" : [ 1 ],
					"shape_scale" : [ 2.0 ],
					"shape_shape" : [ 4 ]
				}

			}
,
			"41" : 			{
				"id" : 41,
				"data" : 				{
					"shape_basis" : [ 4 ],
					"shape_period" : [ 3 ],
					"shape_scale" : [ 1.0 ],
					"shape_shape" : [ 4 ]
				}

			}
,
			"42" : 			{
				"id" : 42,
				"data" : 				{
					"shape_basis" : [ 5 ],
					"shape_period" : [ 4 ],
					"shape_scale" : [ 4.0 ],
					"shape_shape" : [ 4 ]
				}

			}
,
			"43" : 			{
				"id" : 43,
				"data" : 				{
					"shape_basis" : [ 6 ],
					"shape_period" : [ 4 ],
					"shape_scale" : [ 1.0 ],
					"shape_shape" : [ 4 ]
				}

			}
,
			"44" : 			{
				"id" : 44,
				"data" : 				{
					"shape_basis" : [ 7 ],
					"shape_period" : [ 6 ],
					"shape_scale" : [ 1.0 ],
					"shape_shape" : [ 4 ]
				}

			}
,
			"45" : 			{
				"id" : 45,
				"data" : 				{
					"shape_basis" : [ 8 ],
					"shape_period" : [ 6 ],
					"shape_scale" : [ 1.0 ],
					"shape_shape" : [ 4 ]
				}

			}
,
			"46" : 			{
				"id" : 46,
				"data" : 				{
					"shape_basis" : [ 0 ],
					"shape_period" : [ 1 ],
					"shape_scale" : [ 1.0 ],
					"shape_shape" : [ 5 ]
				}

			}
,
			"47" : 			{
				"id" : 47,
				"data" : 				{
					"shape_basis" : [ 1 ],
					"shape_period" : [ 2 ],
					"shape_scale" : [ 2.0 ],
					"shape_shape" : [ 5 ]
				}

			}
,
			"48" : 			{
				"id" : 48,
				"data" : 				{
					"shape_basis" : [ 2 ],
					"shape_period" : [ 4 ],
					"shape_scale" : [ 4.0 ],
					"shape_shape" : [ 5 ]
				}

			}
,
			"49" : 			{
				"id" : 49,
				"data" : 				{
					"shape_basis" : [ 3 ],
					"shape_period" : [ 1 ],
					"shape_scale" : [ 2.0 ],
					"shape_shape" : [ 5 ]
				}

			}
,
			"50" : 			{
				"id" : 50,
				"data" : 				{
					"shape_basis" : [ 4 ],
					"shape_period" : [ 3 ],
					"shape_scale" : [ 1.0 ],
					"shape_shape" : [ 5 ]
				}

			}
,
			"51" : 			{
				"id" : 51,
				"data" : 				{
					"shape_basis" : [ 5 ],
					"shape_period" : [ 4 ],
					"shape_scale" : [ 4.0 ],
					"shape_shape" : [ 5 ]
				}

			}
,
			"52" : 			{
				"id" : 52,
				"data" : 				{
					"shape_basis" : [ 6 ],
					"shape_period" : [ 4 ],
					"shape_scale" : [ 1.0 ],
					"shape_shape" : [ 5 ]
				}

			}
,
			"53" : 			{
				"id" : 53,
				"data" : 				{
					"shape_basis" : [ 7 ],
					"shape_period" : [ 6 ],
					"shape_scale" : [ 1.0 ],
					"shape_shape" : [ 5 ]
				}

			}
,
			"54" : 			{
				"id" : 54,
				"data" : 				{
					"shape_basis" : [ 8 ],
					"shape_period" : [ 6 ],
					"shape_scale" : [ 1.0 ],
					"shape_shape" : [ 5 ]
				}

			}
,
			"55" : 			{
				"id" : 55,
				"data" : 				{
					"shape_basis" : [ 9 ],
					"shape_period" : [ 1 ],
					"shape_scale" : [ 2.0 ],
					"shape_shape" : [ 4 ]
				}

			}
,
			"56" : 			{
				"id" : 56,
				"data" : 				{
					"shape_basis" : [ 9 ],
					"shape_period" : [ 1 ],
					"shape_scale" : [ 2.0 ],
					"shape_shape" : [ 0 ]
				}

			}
,
			"57" : 			{
				"id" : 57,
				"data" : 				{
					"shape_basis" : [ 9 ],
					"shape_period" : [ 1 ],
					"shape_scale" : [ 2.0 ],
					"shape_shape" : [ 1 ]
				}

			}
,
			"58" : 			{
				"id" : 58,
				"data" : 				{
					"shape_basis" : [ 9 ],
					"shape_period" : [ 1 ],
					"shape_scale" : [ 2.0 ],
					"shape_shape" : [ 2 ]
				}

			}
,
			"59" : 			{
				"id" : 59,
				"data" : 				{
					"shape_basis" : [ 9 ],
					"shape_period" : [ 1 ],
					"shape_scale" : [ 2.0 ],
					"shape_shape" : [ 3 ]
				}

			}
,
			"60" : 			{
				"id" : 60,
				"data" : 				{
					"shape_basis" : [ 9 ],
					"shape_period" : [ 1 ],
					"shape_scale" : [ 2.0 ],
					"shape_shape" : [ 4 ]
				}

			}
,
			"61" : 			{
				"id" : 61,
				"data" : 				{
					"shape_basis" : [ 9 ],
					"shape_period" : [ 1 ],
					"shape_scale" : [ 2.0 ],
					"shape_shape" : [ 5 ]
				}

			}

		}

	}

}
